custom_mpl/__init__.py
custom_mpl-0.0.2.dist-info/LICENSE
custom_mpl-0.0.2.dist-info/METADATA
custom_mpl-0.0.2.dist-info/WHEEL
custom_mpl-0.0.2.dist-info/top_level.txt
custom_mpl-0.0.2.dist-info/RECORD
