Metadata-Version: 2.1
Name: custom-mpl
Version: 0.0.2
Summary: A small package of custom matplotlib style sheets
Author-email: Rafal Nojek <rafal.nojek@shell.com>
Project-URL: Homepage, https://github.com/PanNorek/custom_mpl
Project-URL: Bug Tracker, https://github.com/PanNorek/custom_mpl/issues
Classifier: Framework :: Matplotlib
Classifier: Programming Language :: Python :: 3
Classifier: License :: OSI Approved :: MIT License
Classifier: Operating System :: OS Independent
Requires-Python: >=3.7
License-File: LICENSE
